<?xml version="1.0" encoding="utf-8"?>
<Patch>
<Operation Class="PatchOperationSequence">
    <success>Always</success>
    <operations>

<!-- EVA Suit -->
<li Class="CTB_AT_Equipment.EquipmentRestrictionsPatcher">
    <itemLevelRules>
        <li>
            <thingDef>Apparel_SpaceSuitBody</thingDef>
            <techLevelNoResearch>Spacer</techLevelNoResearch>
            <techLevelResearched>Industrial</techLevelResearched>
        </li>
    </itemLevelRules>
</li>

<!-- Kid EVA Suit -->
<li Class="CTB_AT_Equipment.EquipmentRestrictionsPatcher">
    <itemLevelRules>
        <li>
            <thingDef>Apparel_SpaceSuitBodyChild</thingDef>
            <techLevelNoResearch>Spacer</techLevelNoResearch>
            <techLevelResearched>Industrial</techLevelResearched>
        </li>
    </itemLevelRules>
</li>

<!-- EVA Helmet -->
<li Class="CTB_AT_Equipment.EquipmentRestrictionsPatcher">
    <itemLevelRules>
        <li>
            <thingDef>Apparel_SpaceSuitHelmet</thingDef>
            <techLevelNoResearch>Spacer</techLevelNoResearch>
            <techLevelResearched>Industrial</techLevelResearched>
        </li>
    </itemLevelRules>
</li>

<!-- Kid EVA Helmet -->
<li Class="CTB_AT_Equipment.EquipmentRestrictionsPatcher">
    <itemLevelRules>
        <li>
            <thingDef>Apparel_SpaceSuitHelmetChild</thingDef>
            <techLevelNoResearch>Spacer</techLevelNoResearch>
            <techLevelResearched>Industrial</techLevelResearched>
        </li>
    </itemLevelRules>
</li>

<!-- Heavy EVA Suit -->
<li Class="CTB_AT_Equipment.EquipmentRestrictionsPatcher">
    <itemLevelRules>
        <li>
            <thingDef>Apparel_SpaceSuitBodyHeavy</thingDef>
            <techLevelNoResearch>Spacer</techLevelNoResearch>
            <techLevelResearched>Industrial</techLevelResearched>
        </li>
    </itemLevelRules>
</li>

<!-- Heavy EVA Helmet -->
<li Class="CTB_AT_Equipment.EquipmentRestrictionsPatcher">
    <itemLevelRules>
        <li>
            <thingDef>Apparel_SpaceSuitHelmetHeavy</thingDef>
            <techLevelNoResearch>Spacer</techLevelNoResearch>
            <techLevelResearched>Industrial</techLevelResearched>
        </li>
    </itemLevelRules>
</li>

<!-- Survival Belt -->
<li Class="CTB_AT_Equipment.EquipmentRestrictionsPatcher">
    <itemLevelRules>
        <li>
            <thingDef>Apparel_SpaceSurvivalBelt</thingDef>
            <techLevelNoResearch>Spacer</techLevelNoResearch>
            <techLevelResearched>Industrial</techLevelResearched>
        </li>
    </itemLevelRules>
</li>

    </operations>
</Operation>

</Patch>